{
    "title": "View",
    "filename": "View",
    "path": "Grid/Component/View",
    "source": {
        "header": "Includes/Chicane/Grid/Component/View.hpp",
        "namespace": "Chicane::Grid::View",
        "types": [],
        "enums": [],
        "constructors": [
            {
                "accessor": "public",
                "type": "standard",
                "return": {
                    "prefix": "",
                    "name": "",
                    "suffix": "",
                    "path": "",
                    "templates": []
                },
                "name": "View",
                "parameters": [
                    {
                        "type": {
                            "prefix": "const ",
                            "name": "String",
                            "suffix": "&",
                            "path": "Core/String",
                            "templates": []
                        },
                        "name": "inSource"
                    }
                ],
                "modifiers": [],
                "description": "CHICANE_GRID_VIEW_VIEW_DESCRIPTION"
            }
        ],
        "destructors": [],
        "functions": [
            {
                "accessor": "public",
                "type": "standard",
                "return": {
                    "prefix": "",
                    "name": "void",
                    "suffix": "",
                    "path": "",
                    "templates": []
                },
                "name": "setWindow",
                "parameters": [
                    {
                        "type": {
                            "prefix": "",
                            "name": "Window",
                            "suffix": "*",
                            "path": "Core/Window",
                            "templates": []
                        },
                        "name": "inWindow"
                    }
                ],
                "modifiers": [],
                "description": "CHICANE_GRID_VIEW_SETWINDOW_DESCRIPTION"
            },
            {
                "accessor": "public",
                "type": "standard",
                "return": {
                    "prefix": "",
                    "name": "std::vector",
                    "suffix": "",
                    "path": "",
                    "templates": [
                        {
                            "prefix": "",
                            "name": "Component",
                            "suffix": "*",
                            "path": "Grid/Component",
                            "templates": []
                        }
                    ]
                },
                "name": "getChildrenOn",
                "parameters": [
                    {
                        "type": {
                            "prefix": "const ",
                            "name": "Vec2",
                            "suffix": "&",
                            "path": "Core/Math/Vec/Vec2",
                            "templates": []
                        },
                        "name": "inLocation"
                    }
                ],
                "modifiers": [
                    "const"
                ],
                "description": "CHICANE_GRID_VIEW_GETCHILDRENON_DESCRIPTION"
            },
            {
                "accessor": "public",
                "type": "standard",
                "return": {
                    "prefix": "const ",
                    "name": "StyleFile",
                    "suffix": "&",
                    "path": "Grid/Style/File",
                    "templates": []
                },
                "name": "getStyleFile",
                "parameters": [],
                "modifiers": [
                    "const"
                ],
                "description": "CHICANE_GRID_VIEW_GETSTYLEFILE_DESCRIPTION"
            },
            {
                "accessor": "public",
                "type": "standard",
                "return": {
                    "prefix": "",
                    "name": "void",
                    "suffix": "",
                    "path": "",
                    "templates": []
                },
                "name": "importStyleFile",
                "parameters": [
                    {
                        "type": {
                            "prefix": "const ",
                            "name": "FileSystem::Path",
                            "suffix": "&",
                            "path": "Core/FileSystem",
                            "templates": []
                        },
                        "name": "inValue"
                    }
                ],
                "modifiers": [],
                "description": "CHICANE_GRID_VIEW_IMPORTSTYLEFILE_DESCRIPTION"
            },
            {
                "accessor": "protected",
                "type": "standard",
                "return": {
                    "prefix": "",
                    "name": "void",
                    "suffix": "",
                    "path": "",
                    "templates": []
                },
                "name": "handle",
                "parameters": [
                    {
                        "type": {
                            "prefix": "const ",
                            "name": "WindowEvent",
                            "suffix": "&",
                            "path": "Core/Window/Event",
                            "templates": []
                        },
                        "name": "inEvent"
                    }
                ],
                "modifiers": [],
                "description": "CHICANE_GRID_VIEW_HANDLE_DESCRIPTION"
            }
        ],
        "members": [
            {
                "accessor": "public",
                "modifiers": [
                    "static",
                    "constexpr"
                ],
                "type": {
                    "prefix": "const ",
                    "name": "char",
                    "suffix": "*",
                    "path": "",
                    "templates": []
                },
                "name": "TAG_ID",
                "description": "CHICANE_GRID_VIEW_TAG_ID_DESCRIPTION"
            },
            {
                "accessor": "public",
                "modifiers": [
                    "static",
                    "constexpr"
                ],
                "type": {
                    "prefix": "const ",
                    "name": "char",
                    "suffix": "*",
                    "path": "",
                    "templates": []
                },
                "name": "PATH_ATTRIBUTE_NAME",
                "description": "CHICANE_GRID_VIEW_PATH_ATTRIBUTE_NAME_DESCRIPTION"
            },
            {
                "accessor": "protected",
                "modifiers": [],
                "type": {
                    "prefix": "const ",
                    "name": "Window",
                    "suffix": "*",
                    "path": "Core/Window",
                    "templates": []
                },
                "name": "m_window",
                "description": "CHICANE_GRID_VIEW_M_WINDOW_DESCRIPTION"
            },
            {
                "accessor": "protected",
                "modifiers": [],
                "type": {
                    "prefix": "",
                    "name": "WindowEventSubscription",
                    "suffix": "",
                    "path": "Box",
                    "templates": []
                },
                "name": "m_windowEventSubscription",
                "description": "CHICANE_GRID_VIEW_M_WINDOWEVENTSUBSCRIPTION_DESCRIPTION"
            },
            {
                "accessor": "protected",
                "modifiers": [],
                "type": {
                    "prefix": "",
                    "name": "String",
                    "suffix": "",
                    "path": "Core/String",
                    "templates": []
                },
                "name": "m_path",
                "description": "CHICANE_GRID_VIEW_M_PATH_DESCRIPTION"
            },
            {
                "accessor": "protected",
                "modifiers": [],
                "type": {
                    "prefix": "",
                    "name": "StyleFile",
                    "suffix": "",
                    "path": "Grid/Style/File",
                    "templates": []
                },
                "name": "m_styles",
                "description": "CHICANE_GRID_VIEW_M_STYLES_DESCRIPTION"
            }
        ],
        "description": "CHICANE_GRID_VIEW_DESCRIPTION"
    },
    "children": []
}