{
    "title": "StyleImport",
    "filename": "Import",
    "path": "Grid/Style/Import",
    "source": {
        "header": "Includes/Chicane/Grid/Style/Import.hpp",
        "namespace": "Chicane::Grid::StyleImport",
        "types": [
            {
                "name": "List",
                "type": {
                    "prefix": "",
                    "name": "std::vector",
                    "suffix": "",
                    "path": "",
                    "templates": [
                        {
                            "prefix": "",
                            "name": "StyleImport",
                            "suffix": "",
                            "path": "Grid/Style/Import",
                            "templates": []
                        }
                    ]
                },
                "description": "CHICANE_GRID_STYLEIMPORT_LIST_DESCRIPTION"
            }
        ],
        "enums": [],
        "constructors": [
            {
                "accessor": "public",
                "type": "standard",
                "return": {
                    "prefix": "",
                    "name": "",
                    "suffix": "",
                    "path": "",
                    "templates": []
                },
                "name": "StyleImport",
                "parameters": [
                    {
                        "type": {
                            "prefix": "const ",
                            "name": "String",
                            "suffix": "&",
                            "path": "Core/String",
                            "templates": []
                        },
                        "name": "inValue"
                    }
                ],
                "modifiers": [],
                "description": "CHICANE_GRID_STYLEIMPORT_STYLEIMPORT_DESCRIPTION"
            },
            {
                "accessor": "public",
                "type": "standard",
                "return": {
                    "prefix": "",
                    "name": "",
                    "suffix": "",
                    "path": "",
                    "templates": []
                },
                "name": "StyleImport",
                "parameters": [],
                "modifiers": [],
                "description": "CHICANE_GRID_STYLEIMPORT_STYLEIMPORT_DESCRIPTION"
            }
        ],
        "destructors": [],
        "functions": [
            {
                "accessor": "public",
                "type": "standard",
                "return": {
                    "prefix": "",
                    "name": "void",
                    "suffix": "",
                    "path": "",
                    "templates": []
                },
                "name": "parse",
                "parameters": [
                    {
                        "type": {
                            "prefix": "const ",
                            "name": "String",
                            "suffix": "&",
                            "path": "Core/String",
                            "templates": []
                        },
                        "name": "inValue"
                    }
                ],
                "modifiers": [],
                "description": "CHICANE_GRID_STYLEIMPORT_PARSE_DESCRIPTION"
            },
            {
                "accessor": "public",
                "type": "standard",
                "return": {
                    "prefix": "",
                    "name": "void",
                    "suffix": "",
                    "path": "",
                    "templates": []
                },
                "name": "setType",
                "parameters": [
                    {
                        "type": {
                            "prefix": "const ",
                            "name": "String",
                            "suffix": "&",
                            "path": "Core/String",
                            "templates": []
                        },
                        "name": "inValue"
                    }
                ],
                "modifiers": [],
                "description": "CHICANE_GRID_STYLEIMPORT_SETTYPE_DESCRIPTION"
            },
            {
                "accessor": "public",
                "type": "standard",
                "return": {
                    "prefix": "",
                    "name": "void",
                    "suffix": "",
                    "path": "",
                    "templates": []
                },
                "name": "setLocation",
                "parameters": [
                    {
                        "type": {
                            "prefix": "const ",
                            "name": "String",
                            "suffix": "&",
                            "path": "Core/String",
                            "templates": []
                        },
                        "name": "inValue"
                    }
                ],
                "modifiers": [],
                "description": "CHICANE_GRID_STYLEIMPORT_SETLOCATION_DESCRIPTION"
            }
        ],
        "members": [
            {
                "accessor": "public",
                "modifiers": [],
                "type": {
                    "prefix": "",
                    "name": "StyleImportType",
                    "suffix": "",
                    "path": "Grid/Style/Import/Type",
                    "templates": []
                },
                "name": "type",
                "description": "CHICANE_GRID_STYLEIMPORT_TYPE_DESCRIPTION"
            },
            {
                "accessor": "public",
                "modifiers": [],
                "type": {
                    "prefix": "",
                    "name": "StyleLocation",
                    "suffix": "",
                    "path": "Grid/Style/Location",
                    "templates": []
                },
                "name": "location",
                "description": "CHICANE_GRID_STYLEIMPORT_LOCATION_DESCRIPTION"
            }
        ],
        "description": "CHICANE_GRID_STYLEIMPORT_DESCRIPTION"
    },
    "children": []
}